Workbook

Sheet sheet1
A1: Sr. No. | B1: Catogery | C1: Key Responsibility (KR) | D1: KR Discriptions | E1: Frequency | F1: Weightage | G1: Metrics
A2: 1 | B2: Sort Center | C2: SC Vol. & Manpower | D2: 1. Flaging up if any manpower deep or over/lower attainment of vol. 2. Sharing fortnighlty Vol. projection with partner and alignement. | E2: Daily | F2: 0.05 | G2: No Esclation
A3: 2 | C3: SC Inbound and landing | D3: 2. NLH TAT validation and landing profile. | E3: As on when some changes happeing. | F3: 0.05 | G3: No Esclation
A4: 3 | C4: SC DoD Operation and Losses reduction | D4: 1. Working with SC partner for efficient Operation. 2. Ageing control and IRT, label and other exception handling. 3. At facility hardstop losses reduction. 4. COD timely RTO marking and clerance. 5. Daily internal review call participation. 6. Tracker validation and timely update. Internal review, Daily node comliance RCA, Attempt Compliance NLH & At facility breach RCA . | E4: Daily | F4: 0.4 | G4: 1. Node Complaince - > 95%. 2. Bagging Compliance - > 98% 3. At facility losses - < 100 PPM 4. COD > 4 days - ZERO 5. SC Attempt Compliance : >1%
A5: 4 | C5: IB Pendency & Clerance | D5: 1. End to end RCA and control on "at facility" , "Shortage marked" and IB Intransit IB pendency. 2. Recon and pendency closure with upstream nodes on shortage and Intransit pendency. 3. IB Losses reduction and visibility. | E5: Daily | F5: 0.2 | G5: 1. Shortage marked Unresolved : 0.001%. 2. IB Intransit losses : 100 PPM 3. NLH landing performance : > 80% 4. At facility losses : < 100 PPM
A6: 5 | B6: Transportation | C6: OB Pendency & Clerance | D6: 1. End to end control and updates on "OB Intransit" and "Shortage assigned" pendency. 2. Recon and pendecy closure with down stream nodes. 3. Shortage assigned and OB Intransit losses reduction and visibility. | E6: Daily | F6: 0.2 | G6: 1. Shortage assigned Unresolved : 0.001%. 2. OB Intransit losses : 100 PPM
A7: 6 | C7: RLH Design and Utilisation | D7: 1. Maintain the Optimal design coverage of the facility 2. Identify and control RLH design deviation, lower/higher utilisation routes fix it. | E7: When design falls below 95% | F7: 0.05 | G7: 1. Design Coverage : > 95% 2. No escaltion.
A8: 7 | C8: RLH Operation and vendors management | D8: 1. E2E vendor performance management. 2. Route allocation and reduction as per the busssiness requirements. 2. Fixing the Open issues like on-time trip rceipt, POD receipt etc 3. Daily, weekly and Monthly performance visibility. 4. Updating Finance/RLH tracker on D+1. 5. Daily internal review call participation. 6. Validation and timely update of all the trackers like Internal review tracker,vendors input trackers and attempt compliance RLH breaches RCA. | E8: Daily | F8: 0.4 | G8: 1. RLH Attempt Complaince : < 5% 2. Vendor placement and delivery performance : > 95% 3. Finance tracker update : D+1 4. Tracker update completion : D+1
A9: 8 | C9: RLH Cost Control, vendor staboility and Competition | D9: 1. Keeping a track on vehciles utilisation and initiating actions to ensure the maximum utilisation. 2. Vendor wise monthly CPS visibility and Cost reduction initiatives, Starting floating route's. | E9: Daily & Monthly | F9: 0.05 | G9: 1. No over/lower utilisation callout. 2. CPS target : < 4 INR
A10: 9 | B10: Sort Codes Management & Facility layout | C10: Sort Code creation and load balancing. | D10: 1. Cut off/route wise sort code creation needs to be shared within 24 hrs of tagging, if complete information available in the tracker. 2. Stationwise vol balancing and route mapping. 3. Zone to Grid mapping. 4. Maintain the stardard facility laypout and control. | E10: Within 24hrs of request. | F10: 0.15 | G10: 1. Sort code pending should be Zero on > 2 days. 2. Uniform load distribution across all the sorting zones. 3. Zone to Grid mapping accuracy should be > 100% 4. No deviation on standard faciltiy layout and design.
A11: 10 | B11: Consumables | C11: Consumables availability and replenishment and distribution | D11: 1. Track the consumables Inventrory and fullfillment. 2. Ensuring no inventory shortfall. | E11: Daily | F11: 0.05 | G11: 1. Zero shortfall of the consumables Inventory. 2. Consumables daily tracker update.
A12: 11 | B12: Scrap Management | C12: End to End Scrap Management | D12: 1. Regular check of sracp generation (Damage bags, used tags, used bolt seal, corrigated boxes and Lost/damaged, Delivered/duplicate) and plan liqudation. 2. Vendor billing and payment tracking. | E12: Weekly | F12: 0.05 | G12: 1. No accumlation of scraps at the facility. 2. Scrap disposal timely tracker update, Invoice creation and payment closure. 3. In case of Damaged/Duplicate shipment dispoal advanced Delivery Challan creation.
A13: 12 | B13: Excellence Drive | C13: Process Improvements | D13: 1. Improvement initiatives, Kaizens Submission and new new idea for the system excellence. | E13: In general | F13: 0.1 | G13: Montly kaizen/Improvement idea submisson : 1
E16: Sort Center & Other | F16: 1
E17: Transport & Other | F17: 1

Sheet sheet2
A1: Facility Code | B1: Zone | C1: Active Status | D1: Regional Head | E1: Regional Head Mail id | F1: Regional Head Mobile Number | G1: Cluster Head | H1: Cluster Head Mail id | I1: Cluster Head Mobile Number | J1: Area Manager 1 | K1: AM1 Mail id | L1: AM1 Mobile Number | M1: Area Manager 2 | N1: AM2 Mail id | O1: AM2 Mobile Number | P1: Area Manager 3 | Q1: AM3 Mail id | R1: AM3 Mobile Number
A2: AHS | B2: West | C2: Active | D2: Tushar Dongare | E2: tushar.dongare@meesho.com | F2: 8007696417 | G2: Siddharth Chhibber | H2: siddharth.chhibber@meesho.com | I2: 8160593572 | J2: Prakash Lokhande | K2: lokhnade.prakash@meesho.com | L2: 9173700204 | M2: Vishal Mistri | N2: vishal.mistri@meesho.com | O2: 8160776092
A3: BLS | B3: South | C3: Active | D3: Vikrant Pandey | E3: vikrant.pandey@meesho.com | F3: 98030 91594 | G3: Sujesh S | H3: Sujesh.s@meesho.com | I3: 9497320464 | J3: Shivaraj | K3: shivraj.a@meesho.com | L3: 90366 61602 | M3: Gowtham | N3: gowtham.bs@meesho.com | O3: 9663575036
A4: HBS | B4: South | C4: Active | D4: Vikrant Pandey | E4: vikrant.pandey@meesho.com | F4: 98030 91594 | G4: Chamar | H4: chamar.munda1@meesho.com | I4: 6363387963 | J4: Kishore K L | K4: kishor.kl@meesho.com | L4: 7090078440 | M4: Kalyan Reddy | N4: kalyan.reddy@meesho.com | O4: 9164532362
A5: BWS | B5: West | C5: Active | D5: Ajit Gajana Vedak | E5: ajit.vedak@meesho.com | F5: 9004551388 | G5: Suresh Behera | H5: Suresh.behera@meesho.com | I5: 8355872770 | J5: Awwab Kirme | K5: awwab.kirme@meesho.com | L5: 8888726472 | M5: Sagar Rajkumar Khaple | N5: sagar.khaple@meesho.com | O5: 7738879336 | Q5: deepraj.deshmukh@meesho.com | R5: 9226395808
A6: MIS | B6: West | C6: Active | D6: Ajit Gajana Vedak | E6: ajit.vedak@meesho.com | F6: 9004551388 | G6: Abhishek Mhamunkar | H6: abhishek.mhamunkar@meesho.com/manohar.singh@meesho.com | I6: 9969276834/9992913292 | J6: Amar Pansare | K6: amar.pansare@meesho.com | L6: 7767908097 | M6: Rahul Thakare | N6: rahul.thakare@meesho.com | O6: 9922621942
A7: BHS | B7: West | C7: Inactive | D7: Ajit Gajana Vedak | E7: ajit.vedak@meesho.com | F7: 9004551388 | G7: Axendra Singh Chouhan | H7: axendra.chouhan@meesho.com | I7: 7024477807 | J7: Deepak Sharma | K7: deepak.sharma3@meesho.com | L7: 8591085838 | M7: Diwakar saurabh kumar chandrika prasad | N7: saurabhkumar.prashad@meesho.com | O7: 8483900198 | P7: Rajneesh Singh | Q7: rajneesh.singh@meesho.com | R7: 8109234404
A8: BUS | B8: East | C8: Active | D8: Banit Roy | E8: banit.roy@meesho.com | F8: 7001020075 | G8: Deepak Pradhan | H8: deepak.pradhan@meesho.com | I8: 9124377820 | J8: Chandan Kumar Goswami | K8: chandan.goswami@meesho.com | L8: 8700962598 | M8: Jamaluddin Khan | N8: jamaluddin.khan@meesho.com | O8: 9040877464
A9: BBS | B9: East | C9: Active | D9: Banit Roy | E9: banit.roy@meesho.com | F9: 7001020075 | G9: Deepak Pradhan | H9: deepak.pradhan@meesho.com | I9: 9124377820 | J9: Pushpa dhwaja hans | K9: puspadhwaja.hans@meesho.com | L9: 9668843849 | M9: Bibhuti Sethy | N9: bibhuti.sethy@meesho.com | O9: 9439315064
A10: MRS | B10: South | C10: Inactive | D10: Vikrant Pandey | E10: vikrant.pandey@meesho.com | F10: 98030 91594 | G10: Praveen Kumar H | H10: praveenkumar.h@meesho.com | I10: 7358110674 | J10: Bhavani Shankar | K10: bhavani.n@meesho.com | L10: 6385797985 | M10: Sheshathri R | N10: Sheshathri.r@meesho.com | O10: 9360681063 | P10: Prathip Raj | Q10: prathipraj.s@meesho.com | R10: 824 875 4934
A11: DSS | B11: North | C11: Inactive | D11: Prince Shukla | E11: prince.shukla@meesho.com | F11: 8097928258 | G11: Ashish Sharma | H11: ashish.sharma2@meesho.com | I11: 9166587996 | J11: surya pratap | K11: surya.pratap@meesho.com | L11: 9451983805
A12: BMS | B12: North | C12: Active | D12: Dhirender Deswal | E12: dhirender.deswal@meesho.com | F12: 9582713760 | G12: Rahul Kumar Mishra | H12: rahul.mishra3@meesho.com | I12: 9212555696 | J12: Ashish Kumar | K12: ashish.kumar4@meesho.com | L12: 6398993379 | M12: Jasveer Singh | N12: jasveer.singh@meesho.com | O12: 9990061118
A13: LOS | B13: North | C13: Active | D13: Prince Shukla | E13: prince.shukla@meesho.com | F13: 8097928258 | G13: Prince Sharma | H13: prince.sharma@meesho.com | I13: 9257905437 | J13: Kuldeep | K13: Kuldeep.kumar2@meesho.com | L13: 7701835822 | M13: Pinto | N13: pintoo.shah@meesho.com | O13: 8800304177
A14: DHS | B14: South | C14: Inactive | D14: Vikrant Pandey | E14: vikrant.pandey@meesho.com | F14: 98030 91594 | G14: Chamar | H14: chamar.munda1@meesho.com | I14: 6363387963 | J14: Bajendra | K14: bajendra.rauta@meesho.com | L14: 7624961 553 | N14: prashant.pothdar@meesho.com | O14: 9513666556 | P14: Farukh | Q14: faruk.abdullah@meesho.com | R14: 60009 81093
A15: FRS | B15: North | C15: Active | D15: Prince Shukla | E15: prince.shukla@meesho.com | F15: 8097928258 | G15: Keshav Jee | H15: keshav.jee@meesho.com | I15: 7291972416 | J15: Rohit Dubey | K15: rohit.dubey@meesho.com | L15: 8234854147
A16: DLS | B16: North | C16: Active | D16: Dhirender Deswal | E16: dhirender.deswal@meesho.com | F16: 9582713760 | G16: Alan Winsent Martin | H16: alan.martin@meesho.com | I16: 8527384707 | J16: Sombir | K16: sombir@meesho.com | L16: 8278982239 | M16: Arvind Yadav | N16: arvind.yadav@meesho.com | O16: 7056497596
A17: GAS | B17: North | C17: Inactive | D17: Prince Shukla | E17: prince.shukla@meesho.com | F17: 8097928258 | G17: Ashish Sharma | H17: ashish.sharma2@meesho.com | I17: 9166587996
A18: GUS | B18: North | C18: Active | D18: Prince Shukla | E18: prince.shukla@meesho.com | F18: 8097928258 | G18: Vishnu Dutta Mishra | H18: vishnu.mishra1@meesho.com | I18: 6388563799 | J18: surya pratap | K18: surya.pratap@meesho.com | L18: 9451983805 | M18: Akshay Kumar | N18: Akshay.kumar1@meesho.com | O18: 9811699234
A19: DGS1 | B19: North | C19: Active | D19: Prince Shukla | E19: prince.shukla@meesho.com | F19: 8097928258 | G19: Akshit Ahuja | H19: akshit.ahuja@meesho.com | I19: 9266806499 | J19: Rajesh | K19: rajesh.yadav@meesho.com | L19: 9718167299
A20: TVNS | B20: North | C20: Inactive | D20: Prince Shukla | E20: prince.shukla@meesho.com | F20: 8097928258 | G20: Vishnu Dutta Mishra | H20: vishnu.mishra1@meesho.com | I20: 6388563799
A21: GPS | B21: East | C21: Active | D21: Banit Roy | E21: banit.roy@meesho.com | F21: 7001020075 | G21: Suraj kumar | H21: suraj.kumar2@meesho.com | I21: 7979735523 | J21: Satrughan Kumar | K21: satrughan.chourasia@meesho.com | L21: 9570715341 | M21: Alok anupam | N21: alok.anupam@meesho.com | O21: 7903508833
A22: GHS | B22: East | C22: Active | D22: Banit Roy | E22: banit.roy@meesho.com | F22: 7001020075 | G22: Suren Hazarika | H22: suren.hazarika@meesho.com | I22: 6000836880 | J22: Deepjyoti Talukdar | K22: deepjyoti.talukdar@meesho.com | L22: 9387469513 | M22: Brij kishore chauhan | N22: brij.chauhan@meesho.com | O22: 8638190824 | P22: Dipjyoti Dey | Q22: dipjyoti.dey@meesho.com | R22: 9706785585
A23: DBS | B23: East | C23: Active | D23: Banit Roy | E23: banit.roy@meesho.com | F23: 7001020075 | G23: Suren Hazarika | H23: suren.hazarika@meesho.com | I23: 6000836880 | J23: Surya Deep Das | K23: surya.das@meesho.com | L23: 8486874991 | N23: bikash.borah@meesho.com | O23: 8811811385
A24: FKS | B24: North | C24: Active | D24: Dhirender Deswal | E24: dhirender.deswal@meesho.com | F24: 9582713760 | G24: Alan Winsent Martin | H24: alan.martin@meesho.com | I24: 8527384707 | J24: Indu | K24: indu@meesho.com | L24: 7027669312 | M24: Sonu Yadav | N24: sonu.yadav@meesho.com | O24: 8059776160
A25: HGS | B25: East | C25: Inactive | D25: Banit Roy | E25: banit.roy@meesho.com | F25: 7001020075 | G25: Anupam Bal | H25: anupam.bal@meesho.com | I25: 7001483429 | J25: Barun Santra | K25: barun.santra@meesho.com | L25: 6294745548 | M25: Saikat Debnath | N25: saikat.debnath@meesho.com | O25: 70032 86129
A26: HYS | B26: South | C26: Inactive | D26: Vikrant Pandey | E26: vikrant.pandey@meesho.com | F26: 98030 91594 | G26: Pavan Kumar | H26: Pavan.kumar1@meesho.com | I26: 8550010045 | J26: "Pakkula Sathish" | K26: yerrabonia.kumar@meesho.com | L26: 7981426204 | M26: Bommi Nagesh | N26: bommi.nagesh@meesho.com | O26: 9966153878
A27: JBS | B27: West | C27: Active | D27: Ajit Gajana Vedak | E27: ajit.vedak@meesho.com | F27: 9004551388 | G27: Axendra Singh Chouhan | H27: axendra.chouhan@meesho.com | I27: 7024477807 | J27: Gaurav Tayade | K27: gaurav.tayade@meesho.com | L27: 7378792307 | M27: Durgesh kori | N27: durgesh.kori@meesho.com | O27: 7999541157 | P27: Pushpendra kumar patel | Q27: pushpendra.patel@meesho.com | R27: 8319900868
A28: JAS | B28: West | C28: Inactive | D28: Ajit Gajana Vedak | E28: ajit.vedak@meesho.com | F28: 9004551388 | G28: Vikram Singh Rathore | H28: vikram.rathore1@meesho.com | I28: 9413978081 | J28: DUSHYANT KUMAR | K28: dushyant.kumar@meesho.com | L28: 8192051386 | M28: Mantesh Kumar Bairwa | N28: mantesh.bairwa@meesho.com | O28: 9650365405
A29: JPS | B29: West | C29: Active | D29: Ajit Gajana Vedak | E29: ajit.vedak@meesho.com | F29: 9004551388 | G29: Vikram Singh Rathore | H29: vikram.rathore1@meesho.com | I29: 9413978081 | J29: Piyush Singh | K29: piyush.singh@meesho.com | L29: 6352662236 | M29: Abdul Rahuf | N29: abdul.rahuf@meesho.com | O29: 8107269797
A30: JIS | B30: West | C30: Active | D30: Ajit Gajana Vedak | E30: ajit.vedak@meesho.com | F30: 9004551388 | G30: Indu Bala | H30: indu.bala@meesho.com | I30: 8826836418 | J30: Sonu Bairwa | K30: sonu.bairwa@meesho.com | L30: 9358389188 | M30: Rohit Singh Shekhawat | N30: rohit.shekhawat@meesho.com | O30: 9119295841
A31: JUS | B31: West | C31: Inactive | D31: Ajit Gajana Vedak | E31: ajit.vedak@meesho.com | F31: 9004551388 | G31: Vikram Singh Rathore | H31: vikram.rathore1@meesho.com | I31: 9413978081
A32: JJS | B32: West | C32: Active | D32: Ajit Gajana Vedak | E32: ajit.vedak@meesho.com | F32: 9004551388 | G32: Vikram Singh Rathore | H32: vikram.rathore1@meesho.com | I32: 9413978081 | J32: SOURABH SAIN | K32: sourabh.sain@meesho.com | L32: 8952933305 | M32: Gyan Bahadur Jaiswal | N32: gyan.jaiswal@meesho.com | O32: 9318344671
A33: KBS | B33: North | C33: Active | D33: Tushar Sharma | E33: tushar.sharma@meesho.com | F33: 8591391390 | G33: Suraj Chaturvedi | H33: suraj.chaturvedi1@meesho.com | I33: 6393102570 | J33: Amrendra singh | K33: amrendra.singh@meesho.com | L33: 8400863508 | M33: Rituraj gupta | N33: rituraj.gupta@meesho.com | O33: 9696055700
A34: KYS | B34: South | C34: Inactive | D34: Vikrant Pandey | E34: vikrant.pandey@meesho.com | F34: 98030 91594 | G34: Joseph Cherian | H34: joseph.cherian@meesho.com | I34: 8129603774
A35: KOS | B35: East | C35: Active | D35: Banit Roy | E35: banit.roy@meesho.com | F35: 7001020075 | G35: Anupam Bal | H35: anupam.bal@meesho.com | I35: 7001483429 | J35: Pritam Ghosh | K35: pritam.ghosh@meesho.com | L35: 8910122638 | M35: Tapas Bhuinya | N35: tapas.bhuinya@meesho.com | O35: 4ls | P35: Md Sahid Mostafa Tarafdar | Q35: md.tarafdar@meesho.com | R35: 8777826460
A36: LKS | B36: North | C36: Inactive | D36: Tushar Sharma | E36: tushar.sharma@meesho.com | F36: 8591391390 | G36: Suraj Chaturvedi | H36: suraj.chaturvedi1@meesho.com | I36: 6393102570 | J36: Aman Mishra | K36: aman.mishra@meesho.com | L36: 8922876280 | M36: Umakant Maurya | N36: umakant.maurya@meesho.com | O36: 8574176858
A37: VSS | B37: North | C37: Active | D37: Tushar Sharma | E37: tushar.sharma@meesho.com | F37: 8591391390 | G37: Suraj Chaturvedi | H37: suraj.chaturvedi1@meesho.com | I37: 6393102570 | J37: Ramnaresh Dwivedi | K37: ramnaresh.dwivedi@meesho.com | L37: 8090632265 | M37: Ajeet Kumar Singh | N37: ajeet.singh@meesho.com | O37: 7311120913
A38: LUS | B38: North | C38: Inactive | D38: Tushar Sharma | E38: tushar.sharma@meesho.com | F38: 8591391390 | G38: Sourav Nath | H38: sourav.mishra@meesho.com | I38: 9888665095 | J38: Arwinder Singh | K38: arwinder.singh@meesho.com | L38: 8847290992 | M38: Arun Prashar | N38: arun.prasher@meesho.com | O38: 97817 67191
A39: LAS | B39: North | C39: Active | D39: Tushar Sharma | E39: tushar.sharma@meesho.com | F39: 8591391390 | G39: Sourav Nath | H39: sourav.mishra@meesho.com | I39: 9888665095 | J39: Arun Prashar | K39: arun.prasher@meesho.com | L39: 97817 67191 | M39: Gurjit Singh | N39: gurjit.singh@meesho.com | O39: 9872875565
A40: DCS | B40: North | C40: Active | D40: Prince Shukla | E40: prince.shukla@meesho.com | F40: 8097928258 | G40: Mukesh Singh | H40: mukesh.singh@meesho.com | I40: 9999182731 | J40: Bhupender | K40: bhupender@meesho.com | L40: 8708294939 | M40: Sourabh Kumar | N40: sourabh.kumar1@meesho.com | O40: 9888665095
A41: NNS | B41: West | C41: Active | D41: Ajit Gajana Vedak | E41: ajit.vedak@meesho.com | F41: 9004551388 | G41: Vaibhav Bhadake | H41: vaibhav.bhadake1@meesho.com | I41: 97301 82936 | J41: Vivek Kaware | K41: vivek.kaware@meesho.com | L41: 98600 83678 | M41: Shreyash Kapse | N41: shreyash.kapse@meesho.com | O41: 8329814688 | P41: Akshata | Q41: akshata.wanve@meesho.com | R41: 9527375893
A42: PTS | B42: East | C42: Active | D42: Banit Roy | E42: banit.roy@meesho.com | F42: 7001020075 | G42: Himanshu kumar | H42: himanshu.kumar2@meesho.com | I42: 7992351620 | J42: Ravi Ranjan | K42: ravi.ranjan1@meesho.com | L42: 9709250151 | M42: Shashikant Kumar | N42: shashikant.kumar@meesho.com | O42: 9798676855 | P42: Deepak Gupta | Q42: deepak.gupta2@meesho.com | R42: 8840618252
A43: PES | B43: West | C43: Inactive | D43: Ajit Gajana Vedak | E43: ajit.vedak@meesho.com | F43: 9004551388 | G43: Nilesh Parbhane | H43: nilesh.parbhane@meesho.com | I43: 8806659691
A44: NUS | B44: West | C44: Inactive | D44: Ajit Gajana Vedak | E44: ajit.vedak@meesho.com | F44: 9004551388 | G44: Vaibhav Bhadke | H44: vaibhav.bhadake1@meesho.com | I44: 97301 82936 | J44: Vivek Kaware | K44: vivek.kaware@meesho.com | L44: 7020038407 | M44: Narvin Hirekhan | N44: narvin.k@meesho.com | O44: 7875979020
A45: RKS | B45: West | C45: Active | D45: Tushar Dongare | E45: tushar.dongare@meesho.com | F45: 8007696417 | G45: Rohit Kakade | H45: rohit.kakade@meesho.com | I45: 7028402715 | J45: sudeep kumar pandey | K45: sudeep.pandey@meesho.com | L45: 9243766994 | M45: Prakul Jaret | N45: prakul.jaret@meesho.com | O45: 8626930962
A46: RNS | B46: East | C46: Active | D46: Banit Roy | E46: banit.roy@meesho.com | F46: 7001020075 | G46: Suraj kumar | H46: suraj.kumar2@meesho.com | I46: 7979735523 | J46: Kumar Sourav | K46: kumar.sourav@meesho.com | L46: 7004987908 | M46: KANHAI KUMAR THAKUR | N46: kanhai.thakur@meesho.com | O46: 91223 14435
A47: SYS | B47: East | C47: Active | D47: Banit Roy | E47: banit.roy@meesho.com | F47: 7001020075 | G47: Suren Hazarika | H47: suren.hazarika@meesho.com | I47: 6000836880 | J47: Debajit Nath | K47: debajit.nath@meesho.com | L47: 8415860928 | M47: Ratul Paul | N47: ratul.paul@meesho.com | O47: 7035845116 | P47: Joydeep Bagti | Q47: joydeep.bagti@meesho.com | R47: 7002141897
A48: GVS | B48: East | C48: Active | D48: Banit Roy | E48: banit.roy@meesho.com | F48: 7001020075 | G48: Suren Hazarika | H48: suren.hazarika@meesho.com | I48: 6000836880 | J48: Hirakjyoti Sarma | K48: hirakjyoti.sarma@meesho.com | L48: 7002876911 | M48: Pranjit Das | N48: pranjit.das@meesho.com | O48: 7002340731
A49: SLS | B49: East | C49: Active | D49: Banit Roy | E49: banit.roy@meesho.com | F49: 7001020075 | G49: Pradip Kumar | H49: pradip.kumar@meesho.com | I49: 9303626268 | J49: Soubhik Ranjan Sarkar | K49: soubhik.sarkar@meesho.com | L49: 7031340486 | M49: Ravi Rausshan Kumar | N49: Bikash Borah | O49: 8678885974 | P49: Tanusri Pradhan | Q49: tanusri.pardhan@meesho.com | R49: 6289797052
A50: AOS | B50: North | C50: Active | D50: Dhirender Deswal | E50: dhirender.deswal@meesho.com | F50: 9582713760 | G50: Navneet Kumar | H50: navneet.kumar1@meesho.com | I50: 9027246940 | J50: Anuj Kumar | K50: anuj.kumar2@meesho.com | L50: 8285808090 | M50: Vishal Soni | N50: vishal.soni@meesho.com | O50: 9315681948
A51: SPS | B51: West | C51: Active | D51: Tushar Dongare | E51: tushar.dongare@meesho.com | F51: 8007696417 | G51: Mukesh Patil | H51: mukesh.patil@meesho.com | I51: 7698837388 | J51: kishan singh | K51: kishan.singh@meesho.com | L51: 8426846828 | M51: Shubham Shah | N51: shubham.kumar3@meesho.com | O51: 9512281207
A52: SHS | B52: West | C52: Active | D52: Tushar Dongare | E52: tushar.dongare@meesho.com | F52: 8007696417 | G52: Pankaj Tripathi | H52: pankaj.tripathi@meesho.com | I52: 8930909315 | J52: Shubham Mishra | K52: shubham.mishra2@meesho.com | L52: 8690056113 | M52: Nitesh Mehta | N52: nitesh.mehta@meesho.com | O52: 6351502235
A53: SUS | B53: West | C53: Active | D53: Tushar Dongare | E53: tushar.dongare@meesho.com | F53: 8007696417 | G53: Mukesh Patil | H53: mukesh.patil@meesho.com | I53: 7698837388 | J53: Shubham Shah | K53: shubham.kumar3@meesho.com | L53: 9512281207 | M53: kishan singh | N53: kishan.singh@meesho.com | O53: 8426846828
A54: SCS | B54: West | C54: Active | D54: Tushar Dongare | E54: tushar.dongare@meesho.com | F54: 8007696417 | G54: Sudhir Pratap Singh | H54: Sudhir.singh@meesho.com | I54: 7016450894 | J54: Rahul Borude | K54: rahul.borude@meesho.com | L54: 8855915553 | M54: Jagdish Sureshbhai trivedi | N54: trivedi.sureshbhai@meesho.com | O54: 9725104037
A55: SBS | B55: West | C55: Inactive | D55: Tushar Dongare | E55: tushar.dongare@meesho.com | F55: 8007696417 | G55: Pankaj Tripathi | H55: pankaj.tripathi@meesho.com | I55: 8930909315 | J55: Kiran Jadhav | K55: jadav.kiran@meesho.com | L55: 9265430735/ 9033146926 | M55: sanket pundkar | N55: sanket.pundkar@meesho.com | O55: 9812502061
A56: SES | B56: West | C56: Active | D56: Tushar Dongare | E56: tushar.dongare@meesho.com | F56: 8007696417 | G56: Santosh Kumar Soni | H56: santosh.soni@meesho.com | I56: 9099201055 | J56: Akshay Patel | K56: akshaykumar.patel@meesho.com | L56: 7990365788 | M56: Vinod Kalal | N56: kalal.vinod@meesho.com | O56: 9909973188
A57: VWS | B57: South | C57: Active | D57: Vikrant Pandey | E57: vikrant.pandey@meesho.com | F57: 98030 91594 | G57: Kuruba Ravi | H57: Kuruba.ravi@meesho.com | I57: 9133001077 | K57: pagolu.kumar@meesho.com | L57: 70131 58900 | M57: Durga Prasad | N57: malabanti.prasad@meesho.com | O57: 8686720525
A58: VZS | B58: South | C58: Active | D58: Vikrant Pandey | E58: vikrant.pandey@meesho.com | F58: 98030 91594 | G58: Kuruba Ravi | H58: Kuruba.ravi@meesho.com | I58: 9133001077 | J58: Padmanabi Rakesh | K58: padmanabi.rakesh@meesho.com | L58: 8660613753 | M58: gorapalli.srikant | N58: gorapalli.srikant@meesho.com | O58: 8099774097 | P58: Kotnana Prabhu Kumar | Q58: kotnana.kumar@meesho.com | R58: 7337008546
A59: NCRS | B59: North | C59: Active | D59: Prince Shukla | E59: prince.shukla@meesho.com | F59: 8097928258 | G59: Mukesh Singh | H59: mukesh.singh@meesho.com | I59: 9999182731 | J59: Tarun Kumar | K59: tarun.kumar2@meesho.com | L59: 7053637751/8700445098 | M59: VISHAL | N59: vishal2@meesho.com | O59: 9557233383
A60: EUS | B60: North | C60: Active | D60: Prince Shukla | E60: prince.shukla@meesho.com | F60: 8097928258 | G60: Akshit Ahuja | H60: akshit.ahuja@meesho.com | I60: 9266806499 | J60: Mohd Juvair | K60: mohd.juvair@meesho.com | L60: 9410016350 | M60: Shobhit | N60: shobhit@meesho.com | O60: 7704906394
A61: HJS | B61: East | C61: Inactive | D61: Banit Roy | E61: banit.roy@meesho.com | F61: 7001020075 | G61: Himanshu Kumar | H61: himanshu.kumar2@meesho.com | I61: 7992351620 | J61: Adarsh kumar | K61: adarsh.kumar1@meesho.com | L61: 7352052463 | M61: Prahalad Kumar Jha | N61: prahalad.jha@meesho.com | O61: 8448028290 | P61: Prabhakar Kumar | Q61: prabhakar.kumar@meesho.com | R61: 7654669235
A62: GTS | B62: North | C62: Active | D62: Tushar Sharma | E62: tushar.sharma@meesho.com | F62: 8591391390 | G62: Suraj Chaturvedi | H62: suraj.chaturvedi1@meesho.com | I62: 6393102570 | J62: Rakesh Kumar | K62: rakesh.kumar3@meesho.com | L62: 9956219816 | M62: Vishwas Singh | N62: Vishwas.singh@meesho.com | O62: 917880672710
A63: RPS | B63: West | C63: Active | D63: Ajit Gajana Vedak | E63: ajit.vedak@meesho.com | F63: 9004551388 | G63: Vaibhav Bhadke | H63: vaibhav.bhadake1@meesho.com | I63: 97301 82936 | J63: Ramesh | K63: ramesh.hatile@meesho.com | L63: 81205 71922 | M63: Raj Yadav | N63: raj.yadav1@meesho.com | O63: 9926906678 | P63: lmran Khan | Q63: imran.khan2@meesho.com | R63: 8962798776
A64: RWS | B64: East | C64: Active | D64: Banit Roy | E64: banit.roy@meesho.com | F64: 7001020075 | G64: Pradip Kumar | H64: pradip.kumar@meesho.com | I64: 9303626268 | J64: Sk Samirul Islam | K64: samirul.sk@meesho.com | L64: 8637837758 | M64: Abir Baran Roy | N64: abir.roy@meesho.com | O64: 9681185032
A65: PYS | B65: West | C65: Active | D65: Ajit Gajana Vedak | E65: ajit.vedak@meesho.com | F65: 9004551388 | G65: Nilesh Parbhane | H65: nilesh.parbhane@meesho.com | I65: 8806659691 | J65: Rekha Navnath Shinde | K65: rekha.shinde@meesho.com | L65: 7588668369 | M65: Rahul patil | N65: rahul.patil1@meesho.com | O65: 9284643233
A66: INS | B66: West | C66: Inactive | D66: Ajit Gajana Vedak | E66: ajit.vedak@meesho.com | F66: 9004551388 | G66: Axendra Singh Chouhan | H66: axendra.chouhan@meesho.com | I66: 7024477807 | J66: Raj kumar yadav | K66: raj.yadav@meesho.com | L66: 8429844413 | M66: ROSHAN ASHTIYA | N66: roshan.asthiya@meesho.com | O66: 9009149143 | P66: Abhiyudd soni | Q66: abhiyuddh.soni@meesho.com | R66: 8959620999
A67: HWS | B67: East | C67: Active | D67: Banit Roy | E67: banit.roy@meesho.com | F67: 7001020075 | G67: Pradip Kumar | H67: pradip.kumar@meesho.com | I67: 9303626268 | J67: Arindam Dutta | K67: arindam.dutta@meesho.com | L67: 7278927626 | M67: Subrata Mondal | N67: subrata.mondal@meesho.com | O67: 9635977809 | P67: Abhijit Mahato | Q67: abhijit.mahato@meesho.com | R67: 90071 33024
A68: SU8S | B68: West | C68: Active | D68: Tushar Dongare | E68: tushar.dongare@meesho.com | F68: 8007696417 | G68: Santosh Kumar Soni | H68: santosh.soni@meesho.com | I68: 9099201055 | J68: Nilesh vasiya | K68: vasiya.manjibhai@meesho.com | L68: 8488823936 | M68: Hemant Verma | N68: hemant.verma@meesho.com | O68: 7900856570
A69: SU9S | B69: West | C69: Active | D69: Tushar Dongare | E69: tushar.dongare@meesho.com | F69: 8007696417 | G69: Pankaj Tripathi | H69: pankaj.tripathi@meesho.com | I69: 8930909315 | J69: Yash Singh rajpoot | K69: yash.singh2@meesho.com | L69: 9695640704 | M69: Nitesh Mehta | N69: nitesh.mehta@meesho.com | O69: 6351502235
A70: JTS | B70: West | C70: Active | D70: Ajit Gajana Vedak | E70: ajit.vedak@meesho.com | F70: 9004551388 | G70: Indu Bala | H70: indu.bala@meesho.com | I70: 8826836418 | J70: Mahaveer Sharma | K70: mahaveer.sharma@meesho.com | L70: 9610771514 | M70: Vikaskumar Ray | N70: vikaskumar.ray@meesho.com | O70: 9898715522
A71: S10S | B71: West | C71: Active | D71: Tushar Dongare | E71: tushar.dongare@meesho.com | F71: 8007696417 | G71: Santosh Kumar Soni | H71: santosh.soni@meesho.com | I71: 9099201055 | J71: AJay kumar | K71: ajay.kumar4@meesho.com | L71: 9997845742
A72: HUS | B72: North | C72: Active | D72: Dhirender Deswal | E72: dhirender.deswal@meesho.com | F72: 9582713760 | G72: Rahul Kumar Mishra | H72: rahul.mishra3@meesho.com | I72: 9212555696 | J72: Manish Punia | K72: manish1@meesho.com | L72: 8683813743 | M72: Sonu Kumar | N72: sonu.kumar1@meesho.com | O72: 8818005330
A73: POS | B73: East | C73: Active | D73: Banit Roy | E73: banit.roy@meesho.com | F73: 7001020075 | G73: Himanshu kumar | H73: himanshu.kumar2@meesho.com | I73: 7992351620 | J73: Satyanarayana Kumar | K73: satyanarayana.kumar@meesho.com | L73: 8210748344 | M73: Vinay Bhushan | N73: vinay.bhushan@meesho.com | O73: 9334040734 | P73: Chintu Kumar | Q73: chintu.kumar@meesho.com | R73: 7260988849
A74: LDNS | B74: North | C74: Active | D74: Tushar Sharma | E74: tushar.sharma@meesho.com | F74: 8591391390 | G74: Sourav Nath | H74: sourav.mishra@meesho.com | I74: 9888665095 | J74: Arwinder Singh | K74: arwinder.singh@meesho.com | L74: 8847290992 | M74: Mohd Rizwan | N74: mohammad.rizwan@meesho.com | O74: 8090384994
A75: CTS | B75: South | C75: Active | D75: Vikrant Pandey | E75: vikrant.pandey@meesho.com | F75: 98030 91594 | G75: Karthik | H75: karthik.gunasekaran@meesho.com | I75: 9994448658 | J75: Malarvannan V | K75: malarvannan.v@meesho.com | L75: 8668045720 | P75: Karthikeyan Palanisamy | Q75: karthikeyan.p@meesho.com | R75: 8883257427
A76: CFS | B76: South | C76: Active | D76: Vikrant Pandey | E76: vikrant.pandey@meesho.com | F76: 98030 91594 | G76: Karthik | H76: karthik.gunasekaran@meesho.com | I76: 9994448658 | J76: Riyaz khan | K76: riyaskhan@meesho.com | L76: 8825794847 | M76: Reshmi Ramesh | N76: reshmi.ramesh@meesho.com | O76: 7025751238 | P76: Sree ranjith | Q76: sreeranjith.r@meesho.com | R76: 9072731195
A77: A2S | B77: West | C77: Active | D77: Tushar Dongare | E77: tushar.dongare@meesho.com | F77: 8007696417 | G77: Siddharth Chhibber | H77: siddharth.chhibber@meesho.com | I77: 8160593572 | J77: Janak Singh Jadav | K77: jadav.kanaksinh@meesho.com | L77: 9687358442
A78: HTS | B78: East | C78: Active | D78: Banit Roy | E78: banit.roy@meesho.com | F78: 7001020075 | G78: Anupam Bal | H78: anupam.bal@meesho.com | I78: 7001483429 | J78: Sandip Pandit | K78: sandip.pandit@meesho.com | L78: 7449412609 | M78: Deep Kumar Dey | N78: deep.dey@meesho.com | O78: 8617772165
A79: LCS | B79: North | C79: Active | D79: Tushar Sharma | E79: tushar.sharma@meesho.com | F79: 8591391390 | G79: Sandeep Kushwaha | H79: sandeep.kushwaha@meesho.com | I79: 8010417770 | J79: Akash Singh | K79: Akash.singh4@meesho.com | L79: 9670622600 | M79: Dileep kumar | N79: dileep.kashyap@meesho.com | O79: 7880832095
A80: CYS | B80: South | C80: Inactive | D80: Vikrant Pandey | E80: vikrant.pandey@meesho.com | F80: 98030 91594 | G80: Karthik | H80: karthik.gunasekaran@meesho.com | I80: 9994448658 | J80: Ashok kumar. V | K80: ashokkumar.vellingiri@meesho.com | L80: 9025995888
A81: CIS | B81: South | C81: Active | D81: Vikrant Pandey | E81: vikrant.pandey@meesho.com | F81: 98030 91594 | G81: Praveen Kumar H | H81: praveenkumar.h@meesho.com | I81: 7358110674 | J81: Sathish Venkatesh | K81: sathish.venkatesh@meesho.com | L81: 9071717181 | M81: Prathipraj S | N81: sheshathri.r@meesho.com | O81: 824 875 4934 | P81: Dhanalakshmi | Q81: dhanalakshmi@meesho.com | R81: 8754667886
A82: IMS | B82: South | C82: Active | D82: Vikrant Pandey | E82: vikrant.pandey@meesho.com | F82: 98030 91594 | G82: Joseph Cherian | H82: joseph.cherian@meesho.com | I82: 8129603774 | J82: Mohammed Gubaidullah Rahumathullah | K82: mohammed.gr@meesho.com | L82: 8098698690 | M82: Hariprasath M | N82: hariprasath.m@meesho.com | O82: 7904028118
A83: RFS | B83: West | C83: Active | D83: Tushar Dongare | E83: tushar.dongare@meesho.com | F83: 8007696417 | G83: Kranti Chouhan | H83: kranti.chouhan@meesho.com | I83: 9766803981 | J83: Avinash | K83: chavda.ashokbhai@meesho.com | L83: 6354 324 702
A84: JFS | B84: West | C84: Active | D84: Ajit Gajana Vedak | E84: ajit.vedak@meesho.com | F84: 9004551388 | G84: Indu Bala | H84: indu.bala@meesho.com | I84: 8826836418 | J84: Ramavtar Mourya | K84: ramavtar.mourya@meesho.com | L84: 9166141184 | M84: VIKAS PRAJAPAT | N84: vikas.prajapat@meesho.com | O84: 6376369461
A85: JVS | B85: West | C85: Inactive | D85: Ajit Gajana Vedak | E85: ajit.vedak@meesho.com | F85: 9004551388 | G85: Indu Bala | H85: indu.bala@meesho.com | I85: 8826836418
A86: RRS | B86: West | C86: Active | D86: Ajit Gajana Vedak | E86: ajit.vedak@meesho.com | F86: 9004551388 | G86: Vaibhav Bhadke | H86: vaibhav.bhadake1@meesho.com | I86: 97301 82936 | J86: Sekhar Pandey | K86: sekhar.pandey@meesho.com | L86: 9301184536 | M86: Ashok Naik | N86: ashok.naik@meesho.com | O86: 9078951868
A87: PVS | B87: North | C87: Active | D87: Prince Shukla | E87: prince.shukla@meesho.com | F87: 8097928258 | G87: Keshav Jee | H87: keshav.jee@meesho.com | I87: 7291972416 | J87: Jay Narayan Singh | K87: jay.singh@meesho.com | L87: 7078460985 | M87: Ramesh Singh | N87: ramesh.singh@meesho.com | O87: 9953455434
A88: RTS | B88: West | C88: Active | D88: Tushar Dongare | E88: tushar.dongare@meesho.com | F88: 8007696417 | G88: Kranti Chouhan | H88: kranti.chouhan@meesho.com | I88: 9766803981 | J88: Sandip | K88: sandipkumar.saravaiya@meesho.com | L88: 87803 55112
A89: FUS | B89: North | C89: Active | D89: Dhirender Deswal | E89: dhirender.deswal@meesho.com | F89: 9582713760 | G89: Alan Winsent Martin | H89: alan.martin@meesho.com | I89: 8527384707 | J89: Arvind Chauhan | K89: arvind.chauhan@meesho.com | L89: 9813607710 | M89: Banti | N89: banti@meesho.com | O89: 9671292423
A90: SU7S | B90: West | C90: Active | D90: Tushar Dongare | E90: tushar.dongare@meesho.com | F90: 8007696417 | G90: Sudhir Pratap Singh | H90: Sudhir.singh@meesho.com | I90: 7016450894 | J90: Pravin arun mali | K90: pravin.mali@meesho.com | L90: 7202862501
A91: NKS | B91: West | C91: Active | D91: Ajit Gajana Vedak | E91: ajit.vedak@meesho.com | F91: 9004551388 | G91: Abhishek Mhamunkar | H91: abhishek.mhamunkar@meesho.com | I91: 9969276834 | J91: Hemant kumbharde | K91: hemant.kumbharde@meesho.com | L91: 9420477892 | M91: kalpesh sangale | N91: kalpesh.sangale@meesho.com | O91: 9021190556 | Q91: sharad.rathod@meesho.com | R91: 7218717822
A92: SGS1 | B92: West | C92: Active | D92: Tushar Dongare | E92: tushar.dongare@meesho.com | F92: 8007696417 | G92: Santhosh Kumar Soni | H92: santosh.soni@meesho.com | I92: 9099201055 | J92: Shubham Tiwari | K92: shubham.tiwari@meesho.com | L92: 9136364631 | M92: Sandeep Chauhan | N92: sandeep.chauhan@meesho.com | O92: 9021190556
A93: SNPS | B93: North | C93: Active | D93: Dhirender Deswal | E93: dhirender.deswal@meesho.com | F93: 9582713760 | G93: Navneet Kumar | H93: navneet.kumar1@meesho.com | I93: 9027246940 | J93: Kuldeep Kumar | K93: kuldeep.kumar1@meesho.com | L93: 8924962177 | M93: Paramjeet Dahiya | N93: paramjeet.dahiya@meesho.com | O93: 9068120449
A94: AGRS | B94: North | C94: Active | D94: Tushar Sharma | E94: tushar.sharma@meesho.com | F94: 8591391390 | G94: Ranjit | H94: ranjit@meesho.com | I94: 7500636152 | J94: Karan Singh | K94: karan.singh1@meesho.com | L94: 8439394921 | M94: Rana pratap | N94: rana.pratap@meesho.com | O94: 6200326458
A95: HYDS | B95: South | C95: Active | D95: Vikrant Pandey | E95: vikrant.pandey@meesho.com | F95: 98030 91594 | G95: Adigoppula Mallikharjun | H95: mallikharjun@meesho.com | I95: 8074125321 | J95: Pokkula Satish | K95: pokkula.sathish@meesho.com | L95: 9666481545 | M95: CH Shivaji | N95: chinthala.shivaji@meesho.com | O95: 9133204632
A96: DGS2 | B96: North | C96: Active | D96: Dhirender Deswal | E96: dhirender.deswal@meesho.com | F96: 9582713760 | G96: Suresh Kannan | H96: suresh.kannan@meesho.com | I96: 9871651231 | J96: Sunil Thakran | K96: sunil@meesho.com | L96: 9588199624 | M96: Shankar Dagar | N96: shankar.dagar@meesho.com | O96: 9953202277
A97: FRDS | B97: North | C97: Active | D97: Prince Shukla | E97: prince.shukla@meesho.com | F97: 8097928258 | G97: Keshav Jee | H97: keshav.jee@meesho.com | I97: 7291972416 | J97: Kuldeep Kumar | K97: kuldeep.kumar@meesho.com | L97: 9519180136 | M97: Vishwajeet Kumar | N97: vishwajeet.kumar1@meesho.com | O97: 9534779078
A98: BLRS | B98: South | C98: Inactive | D98: Vikrant Pandey | E98: vikrant.pandey@meesho.com | F98: 98030 91594 | G98: Sujesh S | H98: Sujesh.s@meesho.com | I98: 9497320464 | J98: Abhishek Anand | K98: abhishek.anand@meesho.com | L98: 7889485410 | N98: kalyan.reddy@meesho.com | O98: 9164532362
A99: HBLS | B99: South | C99: Active | D99: Vikrant Pandey | E99: vikrant.pandey@meesho.com | F99: 98030 91594 | G99: Chamar | H99: chamar.munda1@meesho.com | I99: 6363387963 | J99: Shivakumar | K99: Shivakumar.c@meesho.com | L99: 9900549403 | M99: Uday | N99: uday.dodamani@meesho.com | O99: 8105466398
A100: S11S | B100: West | C100: Active | D100: Tushar Dongare | E100: tushar.dongare@meesho.com | F100: 8007696417 | G100: Mukesh Patil | H100: mukesh.patil@meesho.com | I100: 7698837388 | J100: Mihir Pawar | K100: pawar.sunil@meesho.com | L100: 7984429471 | M100: Shivam Soni | N100: shivam.soni@meesho.com | O100: 8349966315
...

Sheet sheet3
A1: Zone | B1: Designation | C1: Name | D1: Mail ID | E1: Mobile Number | F1: Password
A2: =_xlfn.XLOOKUP(D2,sheet2!E:E,sheet2!B:B,1,0) -> West | B2: Regional Head | C2: Tushar Dongare | D2: tushar.dongare@meesho.com | E2: 8007696417 | F2: =E2 -> 8007696417
A3: =_xlfn.XLOOKUP(D3,sheet2!E:E,sheet2!B:B,1,0) -> South | B3: Regional Head | C3: Vikrant Pandey | D3: vikrant.pandey@meesho.com | E3: 98030 91594 | F3: =E3 -> 98030 91594
A4: =_xlfn.XLOOKUP(D4,sheet2!E:E,sheet2!B:B,1,0) -> West | B4: Regional Head | C4: Ajit Gajana Vedak | D4: ajit.vedak@meesho.com | E4: 9004551388 | F4: =E4 -> 9004551388
A5: =_xlfn.XLOOKUP(D5,sheet2!E:E,sheet2!B:B,1,0) -> East | B5: Regional Head | C5: Banit Roy | D5: banit.roy@meesho.com | E5: 7001020075 | F5: =E5 -> 7001020075
A6: =_xlfn.XLOOKUP(D6,sheet2!E:E,sheet2!B:B,1,0) -> North | B6: Regional Head | C6: Prince Shukla | D6: prince.shukla@meesho.com | E6: 8097928258 | F6: =E6 -> 8097928258
A7: =_xlfn.XLOOKUP(D7,sheet2!E:E,sheet2!B:B,1,0) -> North | B7: Regional Head | C7: Dhirender Deswal | D7: dhirender.deswal@meesho.com | E7: 9582713760 | F7: =E7 -> 9582713760
A8: =_xlfn.XLOOKUP(D8,sheet2!E:E,sheet2!B:B,1,0) -> North | B8: Regional Head | C8: Tushar Sharma | D8: tushar.sharma@meesho.com | E8: 8591391390 | F8: =E8 -> 8591391390
A9: =_xlfn.XLOOKUP(D9,sheet2!H:H,sheet2!B:B,1,0) -> West | B9: Cluster Head | C9: Siddharth Chhibber | D9: siddharth.chhibber@meesho.com | E9: 8160593572 | F9: =E9 -> 8160593572
A10: =_xlfn.XLOOKUP(D10,sheet2!H:H,sheet2!B:B,1,0) -> South | B10: Cluster Head | C10: Sujesh S | D10: Sujesh.s@meesho.com | E10: 9497320464 | F10: =E10 -> 9497320464
A11: =_xlfn.XLOOKUP(D11,sheet2!H:H,sheet2!B:B,1,0) -> South | B11: Cluster Head | C11: Chamar | D11: chamar.munda1@meesho.com | E11: 6363387963 | F11: =E11 -> 6363387963
A12: =_xlfn.XLOOKUP(D12,sheet2!H:H,sheet2!B:B,1,0) -> West | B12: Cluster Head | C12: Suresh Behera | D12: Suresh.behera@meesho.com | E12: 8355872770 | F12: =E12 -> 8355872770
A13: =_xlfn.XLOOKUP(D13,sheet2!H:H,sheet2!B:B,1,0) -> West | B13: Cluster Head | C13: Abhishek Mhamunkar | D13: abhishek.mhamunkar@meesho.com | E13: 9969276834 | F13: =E13 -> 9969276834
A14: =_xlfn.XLOOKUP(D14,sheet2!H:H,sheet2!B:B,1,0) -> West | B14: Cluster Head | C14: Axendra Singh Chouhan | D14: axendra.chouhan@meesho.com | E14: 7024477807 | F14: =E14 -> 7024477807
A15: =_xlfn.XLOOKUP(D15,sheet2!H:H,sheet2!B:B,1,0) -> East | B15: Cluster Head | C15: Deepak Pradhan | D15: deepak.pradhan@meesho.com | E15: 9124377820 | F15: =E15 -> 9124377820
A16: =_xlfn.XLOOKUP(D16,sheet2!H:H,sheet2!B:B,1,0) -> South | B16: Cluster Head | C16: Praveen Kumar H | D16: praveenkumar.h@meesho.com | E16: 7358110674 | F16: =E16 -> 7358110674
A17: =_xlfn.XLOOKUP(D17,sheet2!H:H,sheet2!B:B,1,0) -> North | B17: Cluster Head | C17: Ashish Sharma | D17: ashish.sharma2@meesho.com | E17: 9166587996 | F17: =E17 -> 9166587996
A18: =_xlfn.XLOOKUP(D18,sheet2!H:H,sheet2!B:B,1,0) -> North | B18: Cluster Head | C18: Rahul Kumar Mishra | D18: rahul.mishra3@meesho.com | E18: 9212555696 | F18: =E18 -> 9212555696
A19: =_xlfn.XLOOKUP(D19,sheet2!H:H,sheet2!B:B,1,0) -> North | B19: Cluster Head | C19: Prince Sharma | D19: prince.sharma@meesho.com | E19: 9257905437 | F19: =E19 -> 9257905437
A20: =_xlfn.XLOOKUP(D20,sheet2!H:H,sheet2!B:B,1,0) -> North | B20: Cluster Head | C20: Keshav Jee | D20: keshav.jee@meesho.com | E20: 7291972416 | F20: =E20 -> 7291972416
... A33: =_xlfn.XLOOKUP(D33,sheet2!H:H,sheet2!B:B,1,0) -> North | B33: Cluster Head | C33: Mukesh Singh | D33: mukesh.singh@meesho.com | E33: 9999182731 | F33: =E33 -> 9999182731
A34: =_xlfn.XLOOKUP(D34,sheet2!H:H,sheet2!B:B,1,0) -> West | B34: Cluster Head | C34: Vaibhav Bhadake | D34: vaibhav.bhadake1@meesho.com | E34: 97301 82936 | F34: =E34 -> 97301 82936
A35: =_xlfn.XLOOKUP(D35,sheet2!H:H,sheet2!B:B,1,0) -> East | B35: Cluster Head | C35: Himanshu kumar | D35: himanshu.kumar2@meesho.com | E35: 7992351620 | F35: =E35 -> 7992351620
A36: =_xlfn.XLOOKUP(D36,sheet2!H:H,sheet2!B:B,1,0) -> West | B36: Cluster Head | C36: Nilesh Parbhane | D36: nilesh.parbhane@meesho.com | E36: 8806659691 | F36: =E36 -> 8806659691
A37: =_xlfn.XLOOKUP(D37,sheet2!H:H,sheet2!B:B,1,0) -> West | B37: Cluster Head | C37: Rohit Kakade | D37: rohit.kakade@meesho.com | E37: 7028402715 | F37: =E37 -> 7028402715
A38: =_xlfn.XLOOKUP(D38,sheet2!H:H,sheet2!B:B,1,0) -> East | B38: Cluster Head | C38: Pradip Kumar | D38: pradip.kumar@meesho.com | E38: 9303626268 | F38: =E38 -> 9303626268
A39: =_xlfn.XLOOKUP(D39,sheet2!H:H,sheet2!B:B,1,0) -> North | B39: Cluster Head | C39: Navneet Kumar | D39: navneet.kumar1@meesho.com | E39: 9027246940 | F39: =E39 -> 9027246940
A40: =_xlfn.XLOOKUP(D40,sheet2!H:H,sheet2!B:B,1,0) -> West | B40: Cluster Head | C40: Mukesh Patil | D40: mukesh.patil@meesho.com | E40: 7698837388 | F40: =E40 -> 7698837388
A41: =_xlfn.XLOOKUP(D41,sheet2!H:H,sheet2!B:B,1,0) -> West | B41: Cluster Head | C41: Pankaj Tripathi | D41: pankaj.tripathi@meesho.com | E41: 8930909315 | F41: =E41 -> 8930909315
A42: =_xlfn.XLOOKUP(D42,sheet2!H:H,sheet2!B:B,1,0) -> West | B42: Cluster Head | C42: Sudhir Pratap Singh | D42: Sudhir.singh@meesho.com | E42: 7016450894 | F42: =E42 -> 7016450894
A43: =_xlfn.XLOOKUP(D43,sheet2!H:H,sheet2!B:B,1,0) -> West | B43: Cluster Head | C43: Santosh Kumar Soni | D43: santosh.soni@meesho.com | E43: 9099201055 | F43: =E43 -> 9099201055
A44: =_xlfn.XLOOKUP(D44,sheet2!H:H,sheet2!B:B,1,0) -> South | B44: Cluster Head | C44: Kuruba Ravi | D44: Kuruba.ravi@meesho.com | E44: 9133001077 | F44: =E44 -> 9133001077
A45: =_xlfn.XLOOKUP(D45,sheet2!H:H,sheet2!B:B,1,0) -> South | B45: Cluster Head | C45: Karthik | D45: karthik.gunasekaran@meesho.com | E45: 9994448658 | F45: =E45 -> 9994448658
A46: =_xlfn.XLOOKUP(D46,sheet2!H:H,sheet2!B:B,1,0) -> North | B46: Cluster Head | C46: Sandeep Kushwaha | D46: sandeep.kushwaha@meesho.com | E46: 8010417770 | F46: =E46 -> 8010417770
... A55: =_xlfn.XLOOKUP(D55,sheet2!H:H,sheet2!B:B,1,0) -> West | B55: Cluster Head | C55: Vijay Kumar Sharma | D55: vijay.sharma1@meesho.com | E55: 9712948673 | F55: =E55 -> 9712948673
A56: =_xlfn.XLOOKUP(D56,sheet2!K:K,sheet2!B:B,1,0) -> West | B56: Area Manager | C56: Prakash Lokhande | D56: lokhnade.prakash@meesho.com | E56: 9173700204 | F56: =E56 -> 9173700204
A57: =_xlfn.XLOOKUP(D57,sheet2!K:K,sheet2!B:B,1,0) -> South | B57: Area Manager | C57: Shivaraj | D57: shivraj.a@meesho.com | E57: 90366 61602 | F57: =E57 -> 90366 61602
A58: =_xlfn.XLOOKUP(D58,sheet2!K:K,sheet2!B:B,1,0) -> South | B58: Area Manager | C58: Kishore K L | D58: kishor.kl@meesho.com | E58: 7090078440 | F58: =E58 -> 7090078440
A59: =_xlfn.XLOOKUP(D59,sheet2!K:K,sheet2!B:B,1,0) -> West | B59: Area Manager | C59: Awwab Kirme | D59: awwab.kirme@meesho.com | E59: 8888726472 | F59: =E59 -> 8888726472
A60: =_xlfn.XLOOKUP(D60,sheet2!K:K,sheet2!B:B,1,0) -> West | B60: Area Manager | C60: Amar Pansare | D60: amar.pansare@meesho.com | E60: 7767908097 | F60: =E60 -> 7767908097
A61: =_xlfn.XLOOKUP(D61,sheet2!K:K,sheet2!B:B,1,0) -> West | B61: Area Manager | C61: Deepak Sharma | D61: deepak.sharma3@meesho.com | E61: 8591085838 | F61: =E61 -> 8591085838
A62: =_xlfn.XLOOKUP(D62,sheet2!K:K,sheet2!B:B,1,0) -> East | B62: Area Manager | C62: Chandan Kumar Goswami | D62: chandan.goswami@meesho.com | E62: 8700962598 | F62: =E62 -> 8700962598
A63: =_xlfn.XLOOKUP(D63,sheet2!K:K,sheet2!B:B,1,0) -> East | B63: Area Manager | C63: Pushpa dhwaja hans | D63: puspadhwaja.hans@meesho.com | E63: 9668843849 | F63: =E63 -> 9668843849
A64: =_xlfn.XLOOKUP(D64,sheet2!K:K,sheet2!B:B,1,0) -> South | B64: Area Manager | C64: Bhavani Shankar | D64: bhavani.n@meesho.com | E64: 6385797985 | F64: =E64 -> 6385797985
A65: =_xlfn.XLOOKUP(D65,sheet2!K:K,sheet2!B:B,1,0) -> North | B65: Area Manager | C65: surya pratap | D65: surya.pratap@meesho.com | E65: 9451983805 | F65: =E65 -> 9451983805
A66: =_xlfn.XLOOKUP(D66,sheet2!K:K,sheet2!B:B,1,0) -> North | B66: Area Manager | C66: Ashish Kumar | D66: ashish.kumar4@meesho.com | E66: 6398993379 | F66: =E66 -> 6398993379
A67: =_xlfn.XLOOKUP(D67,sheet2!K:K,sheet2!B:B,1,0) -> North | B67: Area Manager | C67: Kuldeep | D67: Kuldeep.kumar2@meesho.com | E67: 7701835822 | F67: =E67 -> 7701835822
A68: =_xlfn.XLOOKUP(D68,sheet2!K:K,sheet2!B:B,1,0) -> South | B68: Area Manager | C68: Bajendra | D68: bajendra.rauta@meesho.com | E68: 7624961 553 | F68: =E68 -> 7624961 553
A69: =_xlfn.XLOOKUP(D69,sheet2!K:K,sheet2!B:B,1,0) -> North | B69: Area Manager | C69: Rohit Dubey | D69: rohit.dubey@meesho.com | E69: 8234854147 | F69: =E69 -> 8234854147
A70: =_xlfn.XLOOKUP(D70,sheet2!K:K,sheet2!B:B,1,0) -> North | B70: Area Manager | C70: Sombir | D70: sombir@meesho.com | E70: 8278982239 | F70: =E70 -> 8278982239
A71: =_xlfn.XLOOKUP(D71,sheet2!K:K,sheet2!B:B,1,0) -> North | B71: Area Manager | C71: Rajesh | D71: rajesh.yadav@meesho.com | E71: 9718167299 | F71: =E71 -> 9718167299
A72: =_xlfn.XLOOKUP(D72,sheet2!K:K,sheet2!B:B,1,0) -> East | B72: Area Manager | C72: Satrughan Kumar | D72: satrughan.chourasia@meesho.com | E72: 9570715341 | F72: =E72 -> 9570715341
A73: =_xlfn.XLOOKUP(D73,sheet2!K:K,sheet2!B:B,1,0) -> East | B73: Area Manager | C73: Deepjyoti Talukdar | D73: deepjyoti.talukdar@meesho.com | E73: 9387469513 | F73: =E73 -> 9387469513
A74: =_xlfn.XLOOKUP(D74,sheet2!K:K,sheet2!B:B,1,0) -> East | B74: Area Manager | C74: Surya Deep Das | D74: surya.das@meesho.com | E74: 8486874991 | F74: =E74 -> 8486874991
A75: =_xlfn.XLOOKUP(D75,sheet2!K:K,sheet2!B:B,1,0) -> North | B75: Area Manager | C75: Indu | D75: indu@meesho.com | E75: 7027669312 | F75: =E75 -> 7027669312
A76: =_xlfn.XLOOKUP(D76,sheet2!K:K,sheet2!B:B,1,0) -> East | B76: Area Manager | C76: Barun Santra | D76: barun.santra@meesho.com | E76: 6294745548 | F76: =E76 -> 6294745548
A77: =_xlfn.XLOOKUP(D77,sheet2!K:K,sheet2!B:B,1,0) -> South | B77: Area Manager | C77: "Pakkula Sathish" | D77: yerrabonia.kumar@meesho.com | E77: 7981426204 | F77: =E77 -> 7981426204
A78: =_xlfn.XLOOKUP(D78,sheet2!K:K,sheet2!B:B,1,0) -> West | B78: Area Manager | C78: Gaurav Tayade | D78: gaurav.tayade@meesho.com | E78: 7378792307 | F78: =E78 -> 7378792307
A79: =_xlfn.XLOOKUP(D79,sheet2!K:K,sheet2!B:B,1,0) -> West | B79: Area Manager | C79: DUSHYANT KUMAR | D79: dushyant.kumar@meesho.com | E79: 8192051386 | F79: =E79 -> 8192051386
A80: =_xlfn.XLOOKUP(D80,sheet2!K:K,sheet2!B:B,1,0) -> West | B80: Area Manager | C80: Piyush Singh | D80: piyush.singh@meesho.com | E80: 6352662236 | F80: =E80 -> 6352662236
... A87: =_xlfn.XLOOKUP(D87,sheet2!K:K,sheet2!B:B,1,0) -> North | B87: Area Manager | C87: Arwinder Singh | D87: arwinder.singh@meesho.com | E87: 8847290992 | F87: =E87 -> 8847290992
A88: =_xlfn.XLOOKUP(D88,sheet2!K:K,sheet2!B:B,1,0) -> North | B88: Area Manager | C88: Arun Prashar | D88: arun.prasher@meesho.com | E88: 97817 67191 | F88: =E88 -> 97817 67191
A89: =_xlfn.XLOOKUP(D89,sheet2!K:K,sheet2!B:B,1,0) -> North | B89: Area Manager | C89: Bhupender | D89: bhupender@meesho.com | E89: 8708294939 | F89: =E89 -> 8708294939
A90: =_xlfn.XLOOKUP(D90,sheet2!K:K,sheet2!B:B,1,0) -> West | B90: Area Manager | C90: Vivek Kaware | D90: vivek.kaware@meesho.com | E90: 98600 83678 | F90: =E90 -> 98600 83678
A91: =_xlfn.XLOOKUP(D91,sheet2!K:K,sheet2!B:B,1,0) -> East | B91: Area Manager | C91: Ravi Ranjan | D91: ravi.ranjan1@meesho.com | E91: 9709250151 | F91: =E91 -> 9709250151
A92: =_xlfn.XLOOKUP(D92,sheet2!K:K,sheet2!B:B,1,0) -> West | B92: Area Manager | C92: sudeep kumar pandey | D92: sudeep.pandey@meesho.com | E92: 9243766994 | F92: =E92 -> 9243766994
A93: =_xlfn.XLOOKUP(D93,sheet2!K:K,sheet2!B:B,1,0) -> East | B93: Area Manager | C93: Kumar Sourav | D93: kumar.sourav@meesho.com | E93: 7004987908 | F93: =E93 -> 7004987908
A94: =_xlfn.XLOOKUP(D94,sheet2!K:K,sheet2!B:B,1,0) -> East | B94: Area Manager | C94: Debajit Nath | D94: debajit.nath@meesho.com | E94: 8415860928 | F94: =E94 -> 8415860928
A95: =_xlfn.XLOOKUP(D95,sheet2!K:K,sheet2!B:B,1,0) -> East | B95: Area Manager | C95: Hirakjyoti Sarma | D95: hirakjyoti.sarma@meesho.com | E95: 7002876911 | F95: =E95 -> 7002876911
A96: =_xlfn.XLOOKUP(D96,sheet2!K:K,sheet2!B:B,1,0) -> East | B96: Area Manager | C96: Soubhik Ranjan Sarkar | D96: soubhik.sarkar@meesho.com | E96: 7031340486 | F96: =E96 -> 7031340486
A97: =_xlfn.XLOOKUP(D97,sheet2!K:K,sheet2!B:B,1,0) -> North | B97: Area Manager | C97: Anuj Kumar | D97: anuj.kumar2@meesho.com | E97: 8285808090 | F97: =E97 -> 8285808090
A98: =_xlfn.XLOOKUP(D98,sheet2!K:K,sheet2!B:B,1,0) -> West | B98: Area Manager | C98: kishan singh | D98: kishan.singh@meesho.com | E98: 8426846828 | F98: =E98 -> 8426846828
A99: =_xlfn.XLOOKUP(D99,sheet2!K:K,sheet2!B:B,1,0) -> West | B99: Area Manager | C99: Shubham Mishra | D99: shubham.mishra2@meesho.com | E99: 8690056113 | F99: =E99 -> 8690056113
A100: =_xlfn.XLOOKUP(D100,sheet2!K:K,sheet2!B:B,1,0) -> West | B100: Area Manager | C100: Shubham Shah | D100: shubham.kumar3@meesho.com | E100: 9512281207 | F100: =E100 -> 9512281207
A101: =_xlfn.XLOOKUP(D101,sheet2!K:K,sheet2!B:B,1,0) -> West | B101: Area Manager | C101: Rahul Borude | D101: rahul.borude@meesho.com | E101: 8855915553 | F101: =E101 -> 8855915553
A102: =_xlfn.XLOOKUP(D102,sheet2!K:K,sheet2!B:B,1,0) -> West | B102: Area Manager | C102: Kiran Jadhav | D102: jadav.kiran@meesho.com | E102: 9265430735 | F102: =E102 -> 9265430735
A103: =_xlfn.XLOOKUP(D103,sheet2!K:K,sheet2!B:B,1,0) -> West | B103: Area Manager | C103: Akshay Patel | D103: akshaykumar.patel@meesho.com | E103: 7990365788 | F103: =E103 -> 7990365788
A104: =_xlfn.XLOOKUP(D104,sheet2!K:K,sheet2!B:B,1,0) -> South | B104: Area Manager | C104: Pagolu | D104: pagolu.kumar@meesho.com | E104: 70131 58900 | F104: =E104 -> 70131 58900
A105: =_xlfn.XLOOKUP(D105,sheet2!K:K,sheet2!B:B,1,0) -> South | B105: Area Manager | C105: Padmanabi Rakesh | D105: padmanabi.rakesh@meesho.com | E105: 8660613753 | F105: =E105 -> 8660613753
A106: =_xlfn.XLOOKUP(D106,sheet2!K:K,sheet2!B:B,1,0) -> North | B106: Area Manager | C106: Tarun Kumar | D106: tarun.kumar2@meesho.com | E106: 8700445098 | F106: =E106 -> 8700445098
A107: =_xlfn.XLOOKUP(D107,sheet2!K:K,sheet2!B:B,1,0) -> North | B107: Area Manager | C107: Mohd Juvair | D107: mohd.juvair@meesho.com | E107: 9410016350 | F107: =E107 -> 9410016350
A108: =_xlfn.XLOOKUP(D108,sheet2!K:K,sheet2!B:B,1,0) -> East | B108: Area Manager | C108: Adarsh kumar | D108: adarsh.kumar1@meesho.com | E108: 7352052463 | F108: =E108 -> 7352052463
A109: =_xlfn.XLOOKUP(D109,sheet2!K:K,sheet2!B:B,1,0) -> North | B109: Area Manager | C109: Rakesh Kumar | D109: rakesh.kumar3@meesho.com | E109: 9956219816 | F109: =E109 -> 9956219816
A110: =_xlfn.XLOOKUP(D110,sheet2!K:K,sheet2!B:B,1,0) -> West | B110: Area Manager | C110: Ramesh | D110: ramesh.hatile@meesho.com | E110: 81205 71922 | F110: =E110 -> 81205 71922
A111: =_xlfn.XLOOKUP(D111,sheet2!K:K,sheet2!B:B,1,0) -> East | B111: Area Manager | C111: Sk Samirul Islam | D111: samirul.sk@meesho.com | E111: 8637837758 | F111: =E111 -> 8637837758
A112: =_xlfn.XLOOKUP(D112,sheet2!K:K,sheet2!B:B,1,0) -> West | B112: Area Manager | C112: Rekha Navnath Shinde | D112: rekha.shinde@meesho.com | E112: 7588668369 | F112: =E112 -> 7588668369
A113: =_xlfn.XLOOKUP(D113,sheet2!K:K,sheet2!B:B,1,0) -> West | B113: Area Manager | C113: Raj kumar yadav | D113: raj.yadav@meesho.com | E113: 8429844413 | F113: =E113 -> 8429844413
A114: =_xlfn.XLOOKUP(D114,sheet2!K:K,sheet2!B:B,1,0) -> East | B114: Area Manager | C114: Arindam Dutta | D114: arindam.dutta@meesho.com | E114: 7278927626 | F114: =E114 -> 7278927626
A115: =_xlfn.XLOOKUP(D115,sheet2!K:K,sheet2!B:B,1,0) -> West | B115: Area Manager | C115: Nilesh vasiya | D115: vasiya.manjibhai@meesho.com | E115: 8488823936 | F115: =E115 -> 8488823936
A116: =_xlfn.XLOOKUP(D116,sheet2!K:K,sheet2!B:B,1,0) -> West | B116: Area Manager | C116: Yash Singh rajpoot | D116: yash.singh2@meesho.com | E116: 9695640704 | F116: =E116 -> 9695640704
A117: =_xlfn.XLOOKUP(D117,sheet2!K:K,sheet2!B:B,1,0) -> West | B117: Area Manager | C117: Mahaveer Sharma | D117: mahaveer.sharma@meesho.com | E117: 9610771514 | F117: =E117 -> 9610771514
A118: =_xlfn.XLOOKUP(D118,sheet2!K:K,sheet2!B:B,1,0) -> West | B118: Area Manager | C118: AJay kumar | D118: ajay.kumar4@meesho.com | E118: 9997845742 | F118: =E118 -> 9997845742
A119: =_xlfn.XLOOKUP(D119,sheet2!K:K,sheet2!B:B,1,0) -> North | B119: Area Manager | C119: Manish Punia | D119: manish1@meesho.com | E119: 8683813743 | F119: =E119 -> 8683813743
A120: =_xlfn.XLOOKUP(D120,sheet2!K:K,sheet2!B:B,1,0) -> East | B120: Area Manager | C120: Satyanarayana Kumar | D120: satyanarayana.kumar@meesho.com | E120: 8210748344 | F120: =E120 -> 8210748344
A121: =_xlfn.XLOOKUP(D121,sheet2!K:K,sheet2!B:B,1,0) -> South | B121: Area Manager | C121: Malarvannan V | D121: malarvannan.v@meesho.com | E121: 8668045720 | F121: =E121 -> 8668045720
A122: =_xlfn.XLOOKUP(D122,sheet2!K:K,sheet2!B:B,1,0) -> South | B122: Area Manager | C122: Riyaz khan | D122: riyaskhan@meesho.com | E122: 8825794847 | F122: =E122 -> 8825794847
... A127: =_xlfn.XLOOKUP(D127,sheet2!K:K,sheet2!B:B,1,0) -> South | B127: Area Manager | C127: Mohammed Gubaidullah | D127: mohammed.gr@meesho.com | E127: 8098698690 | F127: =E127 -> 8098698690
A128: =_xlfn.XLOOKUP(D128,sheet2!K:K,sheet2!B:B,1,0) -> West | B128: Area Manager | C128: Avinash | D128: chavda.ashokbhai@meesho.com | E128: 6354 324 702 | F128: =E128 -> 6354 324 702
A129: =_xlfn.XLOOKUP(D129,sheet2!K:K,sheet2!B:B,1,0) -> West | B129: Area Manager | C129: Ramavtar Mourya | D129: ramavtar.mourya@meesho.com | E129: 9166141184 | F129: =E129 -> 9166141184
A130: =_xlfn.XLOOKUP(D130,sheet2!K:K,sheet2!B:B,1,0) -> West | B130: Area Manager | C130: Sekhar Pandey | D130: sekhar.pandey@meesho.com | E130: 9301184536 | F130: =E130 -> 9301184536
...
